crypto/__init__.py
crypto/aesx.py
crypto/crypto.py
crypto/hmacx.py
cryptopie/__init__.py
cryptopie/aesx.py
cryptopie/crypto.py
cryptopie/hmacx.py
cryptopie-1.4.dist-info/LICENCE.md
cryptopie-1.4.dist-info/METADATA
cryptopie-1.4.dist-info/WHEEL
cryptopie-1.4.dist-info/top_level.txt
cryptopie-1.4.dist-info/RECORD
