Metadata-Version: 2.1
Name: cryptopie
Version: 1.4
Summary: cryptopie is library crypto for encrypt data pii
Home-page: https://github.com/dyaksa/cryptopie
Author: Dyaksa Jauharuddin Nour
Author-email: diasnour0395@gmail.com
Classifier: Programming Language :: Python :: 3
Classifier: License :: OSI Approved :: MIT License
Classifier: Operating System :: OS Independent
License-File: LICENCE.md
Requires-Dist: pycryptodome
